MANIFEST.in
README.md
setup.py
TimiPai.egg-info/PKG-INFO
TimiPai.egg-info/SOURCES.txt
TimiPai.egg-info/dependency_links.txt
TimiPai.egg-info/top_level.txt
helloword/__init__.py
helloword/hello.py