Metadata-Version: 1.0
Name: TimiPai
Version: 0.0.1
Summary: A test to deploy my first PyPi packages
Home-page: UNKNOWN
Author: Timi
Author-email: UNKNOWN
License: MIT Licence
Keywords: hello_world
Platform: Linux
